{
  "Title": "Lobsters - Home",
  "Link": "https://lobste.rs/",
  "Description": "",
  "Items": [
    {
      "Title": "Why not tell people to \"simply\" use pyenv, poetry or anaconda",
      "Link": "https://bitecode.substack.com/p/why-not-tell-people-to-simply-use",
      "Description": "\u003cdiv\u003eArticle:\u003cdiv\u003e\u003cbr/\u003e\u003cbr/\u003e\u003cdiv\u003e\u003c/div\u003e\u003cbr/\u003e\u003cbr/\u003e\u003cdiv\u003eLobsters:\u003cdiv\u003e\u003cbr/\u003e\u003cbr/\u003e\u003cdiv\u003e\u003c/div\u003e",
      "Author": "BiteCode",
      "PubDate": "0001-01-01T00:00:00Z"
    },
    {
      "Title": "A simple hash table in C",
      "Link": "https://theleo.zone/posts/hashmap-in-c/",
      "Description": "\u003cdiv\u003eArticle:\u003cdiv\u003e\u003cbr/\u003e\u003cbr/\u003e\u003cdiv\u003e\u003c/div\u003e\u003cbr/\u003e\u003cbr/\u003e\u003cdiv\u003eLobsters:\u003cdiv\u003e\u003cbr/\u003e\u003cbr/\u003e\u003cdiv\u003e\u003c/div\u003e",
      "Author": "robinovitch61",
      "PubDate": "0001-01-01T00:00:00Z"
    },
    {
      "Title": "Lisp Game Jam - \"Wireworld\" in WebAssembly using Spritely's Hoot project",
      "Link": "https://spritely.institute/news/hoot-wireworld-live-in-browser.html",
      "Description": "\u003cdiv\u003eArticle:\u003cdiv\u003e\u003cbr/\u003e\u003cbr/\u003e\u003cdiv\u003e\u003c/div\u003e\u003cbr/\u003e\u003cbr/\u003e\u003cdiv\u003eLobsters:\u003cdiv\u003e\u003cbr/\u003e\u003cbr/\u003e\u003cdiv\u003e\u003c/div\u003e",
      "Author": "dustyweb",
      "PubDate": "0001-01-01T00:00:00Z"
    },
    {
      "Title": "Firefox on Android crash due to Samsung CPU bug",
      "Link": "https://bugzilla.mozilla.org/show_bug.cgi?id=1833315",
      "Description": "\u003cdiv\u003eArticle:\u003cdiv\u003e\u003cbr/\u003e\u003cbr/\u003e\u003cdiv\u003e\u003c/div\u003e\u003cbr/\u003e\u003cbr/\u003e\u003cdiv\u003eLobsters:\u003cdiv\u003e\u003cbr/\u003e\u003cbr/\u003e\u003cdiv\u003e\u003c/div\u003e",
      "Author": "jamesnvc",
      "PubDate": "0001-01-01T00:00:00Z"
    },
    {
      "Title": "An America-less Internet",
      "Link": "https://www.nthbrock.com/posts/americaless-internet/",
      "Description": "\u003cdiv\u003eArticle:\u003cdiv\u003e\u003cbr/\u003e\u003cbr/\u003e\u003cdiv\u003e\u003c/div\u003e\u003cbr/\u003e\u003cbr/\u003e\u003cdiv\u003eLobsters:\u003cdiv\u003e\u003cbr/\u003e\u003cbr/\u003e\u003cdiv\u003e\u003c/div\u003e",
      "Author": "acatton",
      "PubDate": "0001-01-01T00:00:00Z"
    },
    {
      "Title": "Go team discusses creating math/rand/v2",
      "Link": "https://github.com/golang/go/discussions/60751",
      "Description": "\u003cdiv\u003eArticle:\u003cdiv\u003e\u003cbr/\u003e\u003cbr/\u003e\u003cdiv\u003e\u003c/div\u003e\u003cbr/\u003e\u003cbr/\u003e\u003cdiv\u003eLobsters:\u003cdiv\u003e\u003cbr/\u003e\u003cbr/\u003e\u003cdiv\u003e\u003c/div\u003e",
      "Author": "carlmjohnson",
      "PubDate": "0001-01-01T00:00:00Z"
    },
    {
      "Title": "The Adventures of Writing a CHIP8 Emulator - Part 2",
      "Link": "https://benjcal.space/posts/the-adventures-of-writing-a-chip8-emulator-part-2/",
      "Description": "\u003cdiv\u003eArticle:\u003cdiv\u003e\u003cbr/\u003e\u003cbr/\u003e\u003cdiv\u003e\u003c/div\u003e\u003cbr/\u003e\u003cbr/\u003e\u003cdiv\u003eLobsters:\u003cdiv\u003e\u003cbr/\u003e\u003cbr/\u003e\u003cdiv\u003e\u003c/div\u003e",
      "Author": "benj",
      "PubDate": "0001-01-01T00:00:00Z"
    },
    {
      "Title": "GHC Language Extensions Compatibility",
      "Link": "http://ghcaniuse.damianfral.com/",
      "Description": "\u003cdiv\u003eArticle:\u003cdiv\u003e\u003cbr/\u003e\u003cbr/\u003e\u003cdiv\u003e\u003c/div\u003e\u003cbr/\u003e\u003cbr/\u003e\u003cdiv\u003eLobsters:\u003cdiv\u003e\u003cbr/\u003e\u003cbr/\u003e\u003cdiv\u003e\u003c/div\u003e",
      "Author": "puffnfresh",
      "PubDate": "0001-01-01T00:00:00Z"
    },
    {
      "Title": "Adding Dialyzer without the Pain",
      "Link": "https://fly.io/phoenix-files/adding-dialyzer-without-the-pain/",
      "Description": "\u003cdiv\u003eArticle:\u003cdiv\u003e\u003cbr/\u003e\u003cbr/\u003e\u003cdiv\u003e\u003c/div\u003e\u003cbr/\u003e\u003cbr/\u003e\u003cdiv\u003eLobsters:\u003cdiv\u003e\u003cbr/\u003e\u003cbr/\u003e\u003cdiv\u003e\u003c/div\u003e",
      "Author": "Nezteb",
      "PubDate": "0001-01-01T00:00:00Z"
    },
    {
      "Title": "JMP is Launched and Out of Beta",
      "Link": "https://blog.jmp.chat/b/launch-2023",
      "Description": "\u003cdiv\u003eArticle:\u003cdiv\u003e\u003cbr/\u003e\u003cbr/\u003e\u003cdiv\u003e\u003c/div\u003e\u003cbr/\u003e\u003cbr/\u003e\u003cdiv\u003eLobsters:\u003cdiv\u003e\u003cbr/\u003e\u003cbr/\u003e\u003cdiv\u003e\u003c/div\u003e",
      "Author": "JordiGH",
      "PubDate": "0001-01-01T00:00:00Z"
    },
    {
      "Title": "Scripting with Elixir",
      "Link": "https://underjord.io/scripting-with-elixir.html",
      "Description": "\u003cdiv\u003eArticle:\u003cdiv\u003e\u003cbr/\u003e\u003cbr/\u003e\u003cdiv\u003e\u003c/div\u003e\u003cbr/\u003e\u003cbr/\u003e\u003cdiv\u003eLobsters:\u003cdiv\u003e\u003cbr/\u003e\u003cbr/\u003e\u003cdiv\u003e\u003c/div\u003e",
      "Author": "usrme",
      "PubDate": "0001-01-01T00:00:00Z"
    },
    {
      "Title": "hacking root EPP servers to take control of zones",
      "Link": "https://hackcompute.com/hacking-epp-servers/",
      "Description": "\u003cdiv\u003eArticle:\u003cdiv\u003e\u003cbr/\u003e\u003cbr/\u003e\u003cdiv\u003e\u003c/div\u003e\u003cbr/\u003e\u003cbr/\u003e\u003cdiv\u003eLobsters:\u003cdiv\u003e\u003cbr/\u003e\u003cbr/\u003e\u003cdiv\u003e\u003c/div\u003e",
      "Author": "freddyb",
      "PubDate": "0001-01-01T00:00:00Z"
    },
    {
      "Title": "Dealing with deprecations",
      "Link": "https://stitcher.io/blog/dealing-with-deprecations",
      "Description": "\u003cdiv\u003eArticle:\u003cdiv\u003e\u003cbr/\u003e\u003cbr/\u003e\u003cdiv\u003e\u003c/div\u003e\u003cbr/\u003e\u003cbr/\u003e\u003cdiv\u003eLobsters:\u003cdiv\u003e\u003cbr/\u003e\u003cbr/\u003e\u003cdiv\u003e\u003c/div\u003e",
      "Author": "BrenDt",
      "PubDate": "0001-01-01T00:00:00Z"
    },
    {
      "Title": "A note on Metal shader converter",
      "Link": "https://raphlinus.github.io/gpu/2023/06/12/shader-converter.html",
      "Description": "\u003cdiv\u003eArticle:\u003cdiv\u003e\u003cbr/\u003e\u003cbr/\u003e\u003cdiv\u003e\u003c/div\u003e\u003cbr/\u003e\u003cbr/\u003e\u003cdiv\u003eLobsters:\u003cdiv\u003e\u003cbr/\u003e\u003cbr/\u003e\u003cdiv\u003e\u003c/div\u003e",
      "Author": "calvin",
      "PubDate": "0001-01-01T00:00:00Z"
    },
    {
      "Title": "WWDC23: Passkeys",
      "Link": "https://blog.millerti.me/2023/06/10/wwdc23-passkeys/",
      "Description": "\u003cdiv\u003eArticle:\u003cdiv\u003e\u003cbr/\u003e\u003cbr/\u003e\u003cdiv\u003e\u003c/div\u003e\u003cbr/\u003e\u003cbr/\u003e\u003cdiv\u003eLobsters:\u003cdiv\u003e\u003cbr/\u003e\u003cbr/\u003e\u003cdiv\u003e\u003c/div\u003e",
      "Author": "cendyne",
      "PubDate": "0001-01-01T00:00:00Z"
    },
    {
      "Title": "Fuzzing Scheme with AFL++",
      "Link": "https://weinholt.se/articles/fuzzing-scheme-with-aflplusplus/",
      "Description": "\u003cdiv\u003eArticle:\u003cdiv\u003e\u003cbr/\u003e\u003cbr/\u003e\u003cdiv\u003e\u003c/div\u003e\u003cbr/\u003e\u003cbr/\u003e\u003cdiv\u003eLobsters:\u003cdiv\u003e\u003cbr/\u003e\u003cbr/\u003e\u003cdiv\u003e\u003c/div\u003e",
      "Author": "amirouche",
      "PubDate": "0001-01-01T00:00:00Z"
    },
    {
      "Title": "Second-Class References",
      "Link": "https://borretti.me/article/second-class-references",
      "Description": "\u003cdiv\u003eArticle:\u003cdiv\u003e\u003cbr/\u003e\u003cbr/\u003e\u003cdiv\u003e\u003c/div\u003e\u003cbr/\u003e\u003cbr/\u003e\u003cdiv\u003eLobsters:\u003cdiv\u003e\u003cbr/\u003e\u003cbr/\u003e\u003cdiv\u003e\u003c/div\u003e",
      "Author": "adaszko",
      "PubDate": "0001-01-01T00:00:00Z"
    },
    {
      "Title": "Rust Module System Encourages Poor Practices (Comparing to Go)",
      "Link": "https://dmitryfrank.com/articles/rust_module_system_encourages_bad_practices",
      "Description": "\u003cdiv\u003eArticle:\u003cdiv\u003e\u003cbr/\u003e\u003cbr/\u003e\u003cdiv\u003e\u003c/div\u003e\u003cbr/\u003e\u003cbr/\u003e\u003cdiv\u003eLobsters:\u003cdiv\u003e\u003cbr/\u003e\u003cbr/\u003e\u003cdiv\u003e\u003c/div\u003e",
      "Author": "dimonomid",
      "PubDate": "0001-01-01T00:00:00Z"
    },
    {
      "Title": "Chimera Linux is entering alpha stage",
      "Link": "https://chimera-linux.org/news/2023/06/entering-alpha.html",
      "Description": "\u003cdiv\u003eArticle:\u003cdiv\u003e\u003cbr/\u003e\u003cbr/\u003e\u003cdiv\u003e\u003c/div\u003e\u003cbr/\u003e\u003cbr/\u003e\u003cdiv\u003eLobsters:\u003cdiv\u003e\u003cbr/\u003e\u003cbr/\u003e\u003cdiv\u003e\u003c/div\u003e",
      "Author": "iris",
      "PubDate": "0001-01-01T00:00:00Z"
    },
    {
      "Title": "The Computational Content of Isomorphisms (2013)",
      "Link": "https://media.proquest.com/media/hms/ORIG/2/D49uH?_s=rKxUwmbgqKEXAH9RCzAhMuwUWLk%3D",
      "Description": "\u003cdiv\u003eArticle:\u003cdiv\u003e\u003cbr/\u003e\u003cbr/\u003e\u003cdiv\u003e\u003c/div\u003e\u003cbr/\u003e\u003cbr/\u003e\u003cdiv\u003eLobsters:\u003cdiv\u003e\u003cbr/\u003e\u003cbr/\u003e\u003cdiv\u003e\u003c/div\u003e",
      "Author": "5d22b",
      "PubDate": "0001-01-01T00:00:00Z"
    },
    {
      "Title": "Stack Overflow Developer Survey 2023",
      "Link": "https://survey.stackoverflow.co/2023/",
      "Description": "\u003cdiv\u003eArticle:\u003cdiv\u003e\u003cbr/\u003e\u003cbr/\u003e\u003cdiv\u003e\u003c/div\u003e\u003cbr/\u003e\u003cbr/\u003e\u003cdiv\u003eLobsters:\u003cdiv\u003e\u003cbr/\u003e\u003cbr/\u003e\u003cdiv\u003e\u003c/div\u003e",
      "Author": "toastal",
      "PubDate": "0001-01-01T00:00:00Z"
    },
    {
      "Title": "Trading at light speed: designing low latency systems in C++(2022)",
      "Link": "https://www.youtube.com/watch?v=8uAW5FQtcvE",
      "Description": "\u003cdiv\u003eArticle:\u003cdiv\u003e\u003cbr/\u003e\u003cbr/\u003e\u003cdiv\u003e\u003c/div\u003e\u003cbr/\u003e\u003cbr/\u003e\u003cdiv\u003eLobsters:\u003cdiv\u003e\u003cbr/\u003e\u003cbr/\u003e\u003cdiv\u003e\u003c/div\u003e",
      "Author": "dbremner",
      "PubDate": "0001-01-01T00:00:00Z"
    },
    {
      "Title": "What are you doing this week?",
      "Link": "/s/1sqecv/what_are_you_doing_this_week",
      "Description": "\u003cdiv\u003eArticle:\u003cdiv\u003e\u003cbr/\u003e\u003cbr/\u003e\u003cdiv\u003e\u003c/div\u003e\u003cbr/\u003e\u003cbr/\u003e\u003cdiv\u003eLobsters:\u003cdiv\u003e\u003cbr/\u003e\u003cbr/\u003e\u003cdiv\u003e\u003c/div\u003e",
      "Author": "caius",
      "PubDate": "0001-01-01T00:00:00Z"
    },
    {
      "Title": "5NF: The Missing Use Case",
      "Link": "https://datademythed.com/posts/5nf_missing_use_case/",
      "Description": "\u003cdiv\u003eArticle:\u003cdiv\u003e\u003cbr/\u003e\u003cbr/\u003e\u003cdiv\u003e\u003c/div\u003e\u003cbr/\u003e\u003cbr/\u003e\u003cdiv\u003eLobsters:\u003cdiv\u003e\u003cbr/\u003e\u003cbr/\u003e\u003cdiv\u003e\u003c/div\u003e",
      "Author": "squadette",
      "PubDate": "0001-01-01T00:00:00Z"
    },
    {
      "Title": "How to make a QR code with Stable Diffusion",
      "Link": "https://stable-diffusion-art.com/qr-code/",
      "Description": "\u003cdiv\u003eArticle:\u003cdiv\u003e\u003cbr/\u003e\u003cbr/\u003e\u003cdiv\u003e\u003c/div\u003e\u003cbr/\u003e\u003cbr/\u003e\u003cdiv\u003eLobsters:\u003cdiv\u003e\u003cbr/\u003e\u003cbr/\u003e\u003cdiv\u003e\u003c/div\u003e",
      "Author": "Peter5",
      "PubDate": "0001-01-01T00:00:00Z"
    },
    {
      "Title": "Monad Transformers 101",
      "Link": "https://www.williamyaoh.com/posts/2023-06-10-monad-transformers-101.html",
      "Description": "\u003cdiv\u003eArticle:\u003cdiv\u003e\u003cbr/\u003e\u003cbr/\u003e\u003cdiv\u003e\u003c/div\u003e\u003cbr/\u003e\u003cbr/\u003e\u003cdiv\u003eLobsters:\u003cdiv\u003e\u003cbr/\u003e\u003cbr/\u003e\u003cdiv\u003e\u003c/div\u003e",
      "Author": "carlmjohnson",
      "PubDate": "0001-01-01T00:00:00Z"
    },
    {
      "Title": "spacer: CLI tool to insert spacers in command output to provide visual markers of when things happened",
      "Link": "https://github.com/samwho/spacer",
      "Description": "\u003cdiv\u003eArticle:\u003cdiv\u003e\u003cbr/\u003e\u003cbr/\u003e\u003cdiv\u003e\u003c/div\u003e\u003cbr/\u003e\u003cbr/\u003e\u003cdiv\u003eLobsters:\u003cdiv\u003e\u003cbr/\u003e\u003cbr/\u003e\u003cdiv\u003e\u003c/div\u003e",
      "Author": "kellogh",
      "PubDate": "0001-01-01T00:00:00Z"
    },
    {
      "Title": "Minimal Linux VM cross compiledwith Clang and Zig",
      "Link": "https://richiejp.com/zig-cross-compile-ltp-ltx-linux",
      "Description": "\u003cdiv\u003eArticle:\u003cdiv\u003e\u003cbr/\u003e\u003cbr/\u003e\u003cdiv\u003e\u003c/div\u003e\u003cbr/\u003e\u003cbr/\u003e\u003cdiv\u003eLobsters:\u003cdiv\u003e\u003cbr/\u003e\u003cbr/\u003e\u003cdiv\u003e\u003c/div\u003e",
      "Author": "eatonphil",
      "PubDate": "0001-01-01T00:00:00Z"
    },
    {
      "Title": "Modern CSS in Real Life",
      "Link": "https://chriscoyier.net/2023/06/06/modern-css-in-real-life/",
      "Description": "\u003cdiv\u003eArticle:\u003cdiv\u003e\u003cbr/\u003e\u003cbr/\u003e\u003cdiv\u003e\u003c/div\u003e\u003cbr/\u003e\u003cbr/\u003e\u003cdiv\u003eLobsters:\u003cdiv\u003e\u003cbr/\u003e\u003cbr/\u003e\u003cdiv\u003e\u003c/div\u003e",
      "Author": "emrox",
      "PubDate": "0001-01-01T00:00:00Z"
    },
    {
      "Title": "Meet Swift OpenAPI Generator",
      "Link": "https://developer.apple.com/wwdc23/10171",
      "Description": "\u003cdiv\u003eArticle:\u003cdiv\u003e\u003cbr/\u003e\u003cbr/\u003e\u003cdiv\u003e\u003c/div\u003e\u003cbr/\u003e\u003cbr/\u003e\u003cdiv\u003eLobsters:\u003cdiv\u003e\u003cbr/\u003e\u003cbr/\u003e\u003cdiv\u003e\u003c/div\u003e",
      "Author": "kevinc",
      "PubDate": "0001-01-01T00:00:00Z"
    },
    {
      "Title": "Can we be stricter about removing links with modal popups?",
      "Link": "/s/fipfen/can_we_be_stricter_about_removing_links",
      "Description": "\u003cdiv\u003eArticle:\u003cdiv\u003e\u003cbr/\u003e\u003cbr/\u003e\u003cdiv\u003e\u003c/div\u003e\u003cbr/\u003e\u003cbr/\u003e\u003cdiv\u003eLobsters:\u003cdiv\u003e\u003cbr/\u003e\u003cbr/\u003e\u003cdiv\u003e\u003c/div\u003e",
      "Author": "river",
      "PubDate": "0001-01-01T00:00:00Z"
    },
    {
      "Title": "Fractal software for fractal futures",
      "Link": "https://fossil-milk-962.notion.site/Fractal-software-for-fractal-futures-71e515597d6b424c994cae74f3341521?pvs=4",
      "Description": "\u003cdiv\u003eArticle:\u003cdiv\u003e\u003cbr/\u003e\u003cbr/\u003e\u003cdiv\u003e\u003c/div\u003e\u003cbr/\u003e\u003cbr/\u003e\u003cdiv\u003eLobsters:\u003cdiv\u003e\u003cbr/\u003e\u003cbr/\u003e\u003cdiv\u003e\u003c/div\u003e",
      "Author": "chobeat",
      "PubDate": "0001-01-01T00:00:00Z"
    },
    {
      "Title": "Look up word definitions with WordNet and a shell script",
      "Link": "https://tokyoma.de/microsth/pub.php?page=wordnet-script",
      "Description": "\u003cdiv\u003eArticle:\u003cdiv\u003e\u003cbr/\u003e\u003cbr/\u003e\u003cdiv\u003e\u003c/div\u003e\u003cbr/\u003e\u003cbr/\u003e\u003cdiv\u003eLobsters:\u003cdiv\u003e\u003cbr/\u003e\u003cbr/\u003e\u003cdiv\u003e\u003c/div\u003e",
      "Author": "jummo",
      "PubDate": "0001-01-01T00:00:00Z"
    },
    {
      "Title": "Alloydocs updated to Alloy 6",
      "Link": "https://alloy.readthedocs.io/en/latest/language/time.html",
      "Description": "\u003cdiv\u003eArticle:\u003cdiv\u003e\u003cbr/\u003e\u003cbr/\u003e\u003cdiv\u003e\u003c/div\u003e\u003cbr/\u003e\u003cbr/\u003e\u003cdiv\u003eLobsters:\u003cdiv\u003e\u003cbr/\u003e\u003cbr/\u003e\u003cdiv\u003e\u003c/div\u003e",
      "Author": "hwayne",
      "PubDate": "0001-01-01T00:00:00Z"
    },
    {
      "Title": "Monitoring Solar Generation stats with InfluxDB, Telegraf and Solisclo",
      "Link": "https://www.bentasker.co.uk/posts/blog/house-stuff/pulling-soliscloud-stats-into-influxdb-with-telegraf.html",
      "Description": "\u003cdiv\u003eArticle:\u003cdiv\u003e\u003cbr/\u003e\u003cbr/\u003e\u003cdiv\u003e\u003c/div\u003e\u003cbr/\u003e\u003cbr/\u003e\u003cdiv\u003eLobsters:\u003cdiv\u003e\u003cbr/\u003e\u003cbr/\u003e\u003cdiv\u003e\u003c/div\u003e",
      "Author": "eBPF",
      "PubDate": "0001-01-01T00:00:00Z"
    },
    {
      "Title": "Every Signature is Broken: On the Insecurity of Microsoft Office’s OOXML Signatures",
      "Link": "https://www.usenix.org/system/files/sec23summer_235-rohlmann-prepub.pdf",
      "Description": "\u003cdiv\u003eArticle:\u003cdiv\u003e\u003cbr/\u003e\u003cbr/\u003e\u003cdiv\u003e\u003c/div\u003e\u003cbr/\u003e\u003cbr/\u003e\u003cdiv\u003eLobsters:\u003cdiv\u003e\u003cbr/\u003e\u003cbr/\u003e\u003cdiv\u003e\u003c/div\u003e",
      "Author": "calvin",
      "PubDate": "0001-01-01T00:00:00Z"
    }
  ]
}