{
  "Title": "Hacker News - New Links",
  "Link": "https://news.ycombinator.com/newest",
  "Description": "",
  "Items": [
    {
      "Title": "",
      "Link": "",
      "Description": "Article URL: \u003ca href=\"\"\u003e\u003c/a\u003e\n\u003cbr\u003e\u003cbr\u003e\nComments URL: \u003ca href=\"https://news.ycombinator.com/item?id=32313710\"\u003ehttps://news.ycombinator.com/item?id=32313710\u003c/a\u003e\n\u003cbr\u003e\u003cbr\u003e\nPoints: 1 point\n",
      "Author": "",
      "PubDate": "2022-08-02T00:01:24Z"
    },
    {
      "Title": "",
      "Link": "",
      "Description": "Article URL: \u003ca href=\"\"\u003e\u003c/a\u003e\n\u003cbr\u003e\u003cbr\u003e\nComments URL: \u003ca href=\"https://news.ycombinator.com/item?id=32313708\"\u003ehttps://news.ycombinator.com/item?id=32313708\u003c/a\u003e\n\u003cbr\u003e\u003cbr\u003e\nPoints: 1 point\n",
      "Author": "",
      "PubDate": "2022-08-02T00:01:00Z"
    },
    {
      "Title": "",
      "Link": "",
      "Description": "Article URL: \u003ca href=\"\"\u003e\u003c/a\u003e\n\u003cbr\u003e\u003cbr\u003e\nComments URL: \u003ca href=\"https://news.ycombinator.com/item?id=32313704\"\u003ehttps://news.ycombinator.com/item?id=32313704\u003c/a\u003e\n\u003cbr\u003e\u003cbr\u003e\nPoints: 1 point\n",
      "Author": "",
      "PubDate": "2022-08-02T00:00:50Z"
    },
    {
      "Title": "",
      "Link": "",
      "Description": "Article URL: \u003ca href=\"\"\u003e\u003c/a\u003e\n\u003cbr\u003e\u003cbr\u003e\nComments URL: \u003ca href=\"https://news.ycombinator.com/item?id=32313685\"\u003ehttps://news.ycombinator.com/item?id=32313685\u003c/a\u003e\n\u003cbr\u003e\u003cbr\u003e\nPoints: 1 point\n",
      "Author": "",
      "PubDate": "2022-08-01T23:59:11Z"
    },
    {
      "Title": "",
      "Link": "",
      "Description": "Article URL: \u003ca href=\"\"\u003e\u003c/a\u003e\n\u003cbr\u003e\u003cbr\u003e\nComments URL: \u003ca href=\"https://news.ycombinator.com/item?id=32313661\"\u003ehttps://news.ycombinator.com/item?id=32313661\u003c/a\u003e\n\u003cbr\u003e\u003cbr\u003e\nPoints: 1 point\n",
      "Author": "",
      "PubDate": "2022-08-01T23:55:38Z"
    },
    {
      "Title": "",
      "Link": "",
      "Description": "Article URL: \u003ca href=\"\"\u003e\u003c/a\u003e\n\u003cbr\u003e\u003cbr\u003e\nComments URL: \u003ca href=\"https://news.ycombinator.com/item?id=32313659\"\u003ehttps://news.ycombinator.com/item?id=32313659\u003c/a\u003e\n\u003cbr\u003e\u003cbr\u003e\nPoints: 1 point\n",
      "Author": "",
      "PubDate": "2022-08-01T23:55:10Z"
    },
    {
      "Title": "",
      "Link": "",
      "Description": "Article URL: \u003ca href=\"\"\u003e\u003c/a\u003e\n\u003cbr\u003e\u003cbr\u003e\nComments URL: \u003ca href=\"https://news.ycombinator.com/item?id=32313651\"\u003ehttps://news.ycombinator.com/item?id=32313651\u003c/a\u003e\n\u003cbr\u003e\u003cbr\u003e\nPoints: 1 point\n",
      "Author": "",
      "PubDate": "2022-08-01T23:54:14Z"
    },
    {
      "Title": "",
      "Link": "",
      "Description": "Article URL: \u003ca href=\"\"\u003e\u003c/a\u003e\n\u003cbr\u003e\u003cbr\u003e\nComments URL: \u003ca href=\"https://news.ycombinator.com/item?id=32313644\"\u003ehttps://news.ycombinator.com/item?id=32313644\u003c/a\u003e\n\u003cbr\u003e\u003cbr\u003e\nPoints: 1 point\n",
      "Author": "",
      "PubDate": "2022-08-01T23:53:19Z"
    },
    {
      "Title": "",
      "Link": "",
      "Description": "Article URL: \u003ca href=\"\"\u003e\u003c/a\u003e\n\u003cbr\u003e\u003cbr\u003e\nComments URL: \u003ca href=\"https://news.ycombinator.com/item?id=32313638\"\u003ehttps://news.ycombinator.com/item?id=32313638\u003c/a\u003e\n\u003cbr\u003e\u003cbr\u003e\nPoints: 1 point\n",
      "Author": "",
      "PubDate": "2022-08-01T23:52:32Z"
    },
    {
      "Title": "",
      "Link": "",
      "Description": "Article URL: \u003ca href=\"\"\u003e\u003c/a\u003e\n\u003cbr\u003e\u003cbr\u003e\nComments URL: \u003ca href=\"https://news.ycombinator.com/item?id=32313630\"\u003ehttps://news.ycombinator.com/item?id=32313630\u003c/a\u003e\n\u003cbr\u003e\u003cbr\u003e\nPoints: 1 point\n",
      "Author": "",
      "PubDate": "2022-08-01T23:51:52Z"
    },
    {
      "Title": "",
      "Link": "",
      "Description": "Article URL: \u003ca href=\"\"\u003e\u003c/a\u003e\n\u003cbr\u003e\u003cbr\u003e\nComments URL: \u003ca href=\"https://news.ycombinator.com/item?id=32313626\"\u003ehttps://news.ycombinator.com/item?id=32313626\u003c/a\u003e\n\u003cbr\u003e\u003cbr\u003e\nPoints: 1 point\n",
      "Author": "",
      "PubDate": "2022-08-01T23:51:20Z"
    },
    {
      "Title": "",
      "Link": "",
      "Description": "Article URL: \u003ca href=\"\"\u003e\u003c/a\u003e\n\u003cbr\u003e\u003cbr\u003e\nComments URL: \u003ca href=\"https://news.ycombinator.com/item?id=32313624\"\u003ehttps://news.ycombinator.com/item?id=32313624\u003c/a\u003e\n\u003cbr\u003e\u003cbr\u003e\nPoints: 1 point\n",
      "Author": "",
      "PubDate": "2022-08-01T23:51:13Z"
    },
    {
      "Title": "",
      "Link": "",
      "Description": "Article URL: \u003ca href=\"\"\u003e\u003c/a\u003e\n\u003cbr\u003e\u003cbr\u003e\nComments URL: \u003ca href=\"https://news.ycombinator.com/item?id=32313615\"\u003ehttps://news.ycombinator.com/item?id=32313615\u003c/a\u003e\n\u003cbr\u003e\u003cbr\u003e\nPoints: 1 point\n",
      "Author": "",
      "PubDate": "2022-08-01T23:50:05Z"
    },
    {
      "Title": "",
      "Link": "",
      "Description": "Article URL: \u003ca href=\"\"\u003e\u003c/a\u003e\n\u003cbr\u003e\u003cbr\u003e\nComments URL: \u003ca href=\"https://news.ycombinator.com/item?id=32313587\"\u003ehttps://news.ycombinator.com/item?id=32313587\u003c/a\u003e\n\u003cbr\u003e\u003cbr\u003e\nPoints: 1 point\n",
      "Author": "",
      "PubDate": "2022-08-01T23:45:22Z"
    },
    {
      "Title": "",
      "Link": "",
      "Description": "Article URL: \u003ca href=\"\"\u003e\u003c/a\u003e\n\u003cbr\u003e\u003cbr\u003e\nComments URL: \u003ca href=\"https://news.ycombinator.com/item?id=32313586\"\u003ehttps://news.ycombinator.com/item?id=32313586\u003c/a\u003e\n\u003cbr\u003e\u003cbr\u003e\nPoints: 1 point\n",
      "Author": "",
      "PubDate": "2022-08-01T23:45:17Z"
    },
    {
      "Title": "",
      "Link": "",
      "Description": "Article URL: \u003ca href=\"\"\u003e\u003c/a\u003e\n\u003cbr\u003e\u003cbr\u003e\nComments URL: \u003ca href=\"https://news.ycombinator.com/item?id=32313579\"\u003ehttps://news.ycombinator.com/item?id=32313579\u003c/a\u003e\n\u003cbr\u003e\u003cbr\u003e\nPoints: 1 point\n",
      "Author": "",
      "PubDate": "2022-08-01T23:44:47Z"
    },
    {
      "Title": "",
      "Link": "",
      "Description": "Article URL: \u003ca href=\"\"\u003e\u003c/a\u003e\n\u003cbr\u003e\u003cbr\u003e\nComments URL: \u003ca href=\"https://news.ycombinator.com/item?id=32313574\"\u003ehttps://news.ycombinator.com/item?id=32313574\u003c/a\u003e\n\u003cbr\u003e\u003cbr\u003e\nPoints: 2 points\n",
      "Author": "",
      "PubDate": "2022-08-01T23:44:07Z"
    },
    {
      "Title": "",
      "Link": "",
      "Description": "Article URL: \u003ca href=\"\"\u003e\u003c/a\u003e\n\u003cbr\u003e\u003cbr\u003e\nComments URL: \u003ca href=\"https://news.ycombinator.com/item?id=32313540\"\u003ehttps://news.ycombinator.com/item?id=32313540\u003c/a\u003e\n\u003cbr\u003e\u003cbr\u003e\nPoints: 2 points\n",
      "Author": "",
      "PubDate": "2022-08-01T23:39:36Z"
    },
    {
      "Title": "",
      "Link": "",
      "Description": "Article URL: \u003ca href=\"\"\u003e\u003c/a\u003e\n\u003cbr\u003e\u003cbr\u003e\nComments URL: \u003ca href=\"https://news.ycombinator.com/item?id=32313525\"\u003ehttps://news.ycombinator.com/item?id=32313525\u003c/a\u003e\n\u003cbr\u003e\u003cbr\u003e\nPoints: 2 points\n",
      "Author": "",
      "PubDate": "2022-08-01T23:37:33Z"
    },
    {
      "Title": "",
      "Link": "",
      "Description": "Article URL: \u003ca href=\"\"\u003e\u003c/a\u003e\n\u003cbr\u003e\u003cbr\u003e\nComments URL: \u003ca href=\"https://news.ycombinator.com/item?id=32313515\"\u003ehttps://news.ycombinator.com/item?id=32313515\u003c/a\u003e\n\u003cbr\u003e\u003cbr\u003e\nPoints: 2 points\n",
      "Author": "",
      "PubDate": "2022-08-01T23:36:45Z"
    },
    {
      "Title": "",
      "Link": "",
      "Description": "Article URL: \u003ca href=\"\"\u003e\u003c/a\u003e\n\u003cbr\u003e\u003cbr\u003e\nComments URL: \u003ca href=\"https://news.ycombinator.com/item?id=32313509\"\u003ehttps://news.ycombinator.com/item?id=32313509\u003c/a\u003e\n\u003cbr\u003e\u003cbr\u003e\nPoints: 1 point\n",
      "Author": "",
      "PubDate": "2022-08-01T23:35:47Z"
    },
    {
      "Title": "",
      "Link": "",
      "Description": "Article URL: \u003ca href=\"\"\u003e\u003c/a\u003e\n\u003cbr\u003e\u003cbr\u003e\nComments URL: \u003ca href=\"https://news.ycombinator.com/item?id=32313499\"\u003ehttps://news.ycombinator.com/item?id=32313499\u003c/a\u003e\n\u003cbr\u003e\u003cbr\u003e\nPoints: 2 points\n",
      "Author": "",
      "PubDate": "2022-08-01T23:34:50Z"
    },
    {
      "Title": "",
      "Link": "",
      "Description": "Article URL: \u003ca href=\"\"\u003e\u003c/a\u003e\n\u003cbr\u003e\u003cbr\u003e\nComments URL: \u003ca href=\"https://news.ycombinator.com/item?id=32313491\"\u003ehttps://news.ycombinator.com/item?id=32313491\u003c/a\u003e\n\u003cbr\u003e\u003cbr\u003e\nPoints: 1 point\n",
      "Author": "",
      "PubDate": "2022-08-01T23:33:27Z"
    },
    {
      "Title": "",
      "Link": "",
      "Description": "Article URL: \u003ca href=\"\"\u003e\u003c/a\u003e\n\u003cbr\u003e\u003cbr\u003e\nComments URL: \u003ca href=\"https://news.ycombinator.com/item?id=32313474\"\u003ehttps://news.ycombinator.com/item?id=32313474\u003c/a\u003e\n\u003cbr\u003e\u003cbr\u003e\nPoints: 1 point\n",
      "Author": "",
      "PubDate": "2022-08-01T23:31:15Z"
    },
    {
      "Title": "",
      "Link": "",
      "Description": "Article URL: \u003ca href=\"\"\u003e\u003c/a\u003e\n\u003cbr\u003e\u003cbr\u003e\nComments URL: \u003ca href=\"https://news.ycombinator.com/item?id=32313468\"\u003ehttps://news.ycombinator.com/item?id=32313468\u003c/a\u003e\n\u003cbr\u003e\u003cbr\u003e\nPoints: 1 point\n",
      "Author": "",
      "PubDate": "2022-08-01T23:30:15Z"
    },
    {
      "Title": "",
      "Link": "",
      "Description": "Article URL: \u003ca href=\"\"\u003e\u003c/a\u003e\n\u003cbr\u003e\u003cbr\u003e\nComments URL: \u003ca href=\"https://news.ycombinator.com/item?id=32313454\"\u003ehttps://news.ycombinator.com/item?id=32313454\u003c/a\u003e\n\u003cbr\u003e\u003cbr\u003e\nPoints: 1 point\n",
      "Author": "",
      "PubDate": "2022-08-01T23:28:51Z"
    },
    {
      "Title": "",
      "Link": "",
      "Description": "Article URL: \u003ca href=\"\"\u003e\u003c/a\u003e\n\u003cbr\u003e\u003cbr\u003e\nComments URL: \u003ca href=\"https://news.ycombinator.com/item?id=32313444\"\u003ehttps://news.ycombinator.com/item?id=32313444\u003c/a\u003e\n\u003cbr\u003e\u003cbr\u003e\nPoints: 1 point\n",
      "Author": "",
      "PubDate": "2022-08-01T23:27:09Z"
    },
    {
      "Title": "",
      "Link": "",
      "Description": "Article URL: \u003ca href=\"\"\u003e\u003c/a\u003e\n\u003cbr\u003e\u003cbr\u003e\nComments URL: \u003ca href=\"https://news.ycombinator.com/item?id=32313441\"\u003ehttps://news.ycombinator.com/item?id=32313441\u003c/a\u003e\n\u003cbr\u003e\u003cbr\u003e\nPoints: 2 points\n",
      "Author": "",
      "PubDate": "2022-08-01T23:26:35Z"
    },
    {
      "Title": "",
      "Link": "",
      "Description": "Article URL: \u003ca href=\"\"\u003e\u003c/a\u003e\n\u003cbr\u003e\u003cbr\u003e\nComments URL: \u003ca href=\"https://news.ycombinator.com/item?id=32313431\"\u003ehttps://news.ycombinator.com/item?id=32313431\u003c/a\u003e\n\u003cbr\u003e\u003cbr\u003e\nPoints: 2 points\n",
      "Author": "",
      "PubDate": "2022-08-01T23:25:28Z"
    },
    {
      "Title": "",
      "Link": "",
      "Description": "Article URL: \u003ca href=\"\"\u003e\u003c/a\u003e\n\u003cbr\u003e\u003cbr\u003e\nComments URL: \u003ca href=\"https://news.ycombinator.com/item?id=32313415\"\u003ehttps://news.ycombinator.com/item?id=32313415\u003c/a\u003e\n\u003cbr\u003e\u003cbr\u003e\nPoints: 1 point\n",
      "Author": "",
      "PubDate": "2022-08-01T23:24:30Z"
    }
  ]
}